twed.cp38-win_amd64.pyd
pytwed/__init__.py
pytwed/fast_twed.c
pytwed/slow_twed.py
pytwed/twed.c
pytwed/twed.h
pytwed-1.0.9.dist-info/LICENSE
pytwed-1.0.9.dist-info/METADATA
pytwed-1.0.9.dist-info/WHEEL
pytwed-1.0.9.dist-info/top_level.txt
pytwed-1.0.9.dist-info/RECORD
