Metadata-Version: 2.1
Name: pytwed
Version: 1.0.9
Summary: This is a python wrapper for Marteau's reference implementation of his 2009 paper introducing the Time Warped Edit Distance (TWED).
Home-page: https://github.com/jzumer/pytwed
Author: Pierre-Francois Marteau, JZ, Marcus Voss
License: MIT License
Platform: UNKNOWN
Classifier: Programming Language :: Python :: 3
Classifier: Programming Language :: C
Classifier: License :: OSI Approved :: MIT License
Classifier: Intended Audience :: Science/Research
Classifier: Topic :: Scientific/Engineering
